anbima_calendar/__init__.py
anbima_calendar/date.py
anbima_calendar/errors.py
anbima_calendar/holidays.py
anbima_calendar-0.1.1.dist-info/LICENSE
anbima_calendar-0.1.1.dist-info/METADATA
anbima_calendar-0.1.1.dist-info/WHEEL
anbima_calendar-0.1.1.dist-info/RECORD
