Metadata-Version: 2.1
Name: anbima_calendar
Version: 0.1.1
Summary: Helper functions to handle banking holidays in Brazil
Home-page: https://anbima-calendar.readthedocs.io/en/latest/
License: MIT
Author: Rafael Izidoro
Author-email: izidoro.me@gmail.com
Requires-Python: >=3.11,<4.0
Classifier: License :: OSI Approved :: MIT License
Classifier: Programming Language :: Python :: 3
Classifier: Programming Language :: Python :: 3.11
Project-URL: Documentation, https://anbima-calendar.readthedocs.io/en/latest/
Project-URL: Repository, https://github.com/rizidoro/anbima_calendar
